{
  "ads": "реклама",
  "animation": "анимация",
  "architecture": "архитектура",
  "arrays": "массивы",
  "blog": "блог",
  "browsers": "браузеры",
  "bugs": "баги",
  "build": "сборка",
  "challenges": "челленджи",
  "code-style": "стиль-кода",
  "conferences": "конференции",
  "debugging": "отладка",
  "development": "разработка",
  "digest": "дайджест",
  "education": "обучение",
  "editors": "редакторы",
  "english": "английский",
  "easter-eggs": "пасхалки",
  "experiments": "эксперименты",
  "extensions": "расширения",
  "fonts": "шрифты",
  "frameworks": "фреймворки",
  "frontend": "фронтенд",
  "game": "игра",
  "graphics": "графика",
  "habits": "привычки",
  "images": "изображения",
  "internet": "интернет",
  "interviews": "собеседования",
  "lifehacks": "лайфхаки",
  "links": "ссылки",
  "media-queries": "медиа-запросы",
  "migration": "миграция",
  "non-development": "не разработка",
  "optimization": "оптимизация",
  "performance": "производительность",
  "plugins": "плагины",
  "refactoring": "рефакторинг",
  "reviews": "отзывы",
  "scroll": "скролл",
  "self-improvement": "саморазвитие",
  "servers": "серверы",
  "service": "сервис",
  "social": "соцсети",
  "testing": "тестирование",
  "tips": "советы",
  "tools": "инструменты",
  "typography": "типографика",
  "books": "книги",
  "network": "сеть",
  "neural network": "нейросети",
  "video": "видео"
}
